colorboy/__init__.py
colorboy/bg_colors.py
colorboy/colors.py
colorboy/styles.py
colorboy-1.0.3.dist-info/entry_points.txt
colorboy-1.0.3.dist-info/WHEEL
colorboy-1.0.3.dist-info/METADATA
colorboy-1.0.3.dist-info/RECORD
