Metadata-Version: 2.1
Name: colorboy
Version: 1.0.3
Summary: Easily add color to your strings
Home-page: https://github.com/probablykasper/colorboy-py
Keywords: colorboy,color,terminal,chalk,colorama,termcolor
Author: kasper.space
Classifier: Programming Language :: Python :: 2
Classifier: Programming Language :: Python :: 2.7
Classifier: Programming Language :: Python :: 3
Classifier: Programming Language :: Python :: 3.4
Classifier: Programming Language :: Python :: 3.5
Classifier: Programming Language :: Python :: 3.6
Classifier: Programming Language :: Python :: 3.7
Classifier: Programming Language :: Python :: 3.8
Project-URL: Repository, https://github.com/probablykasper/colorboy-py
